parsnips/__init__.py
parsnips/extractor.py
parsnips/main.py
parsnips-2.0.1.dist-info/METADATA
parsnips-2.0.1.dist-info/WHEEL
parsnips-2.0.1.dist-info/entry_points.txt
parsnips-2.0.1.dist-info/licenses/LICENSE
parsnips-2.0.1.dist-info/RECORD
