Metadata-Version: 2.4
Name: parsnips
Version: 2.0.1
Summary: Generate, search, and cite SWHIDs for Python code fragments like classes, functions, and expressions.
Project-URL: Homepage, https://github.com/willynilly/parsnips
Project-URL: Documentation, https://github.com/willynilly/parsnips#readme
Project-URL: Issues, https://github.com/willynilly/parsnips/issues
Project-URL: Source, https://github.com/willynilly/parsnips
Author-email: Will Riley <wanderingwill@gmail.com>
License-Expression: Apache-2.0
License-File: LICENSE
Keywords: SWHID,Software Heritage,abstract parse tree,citation,code fragment,persistent identifier
Classifier: Development Status :: 3 - Alpha
Classifier: Intended Audience :: Developers
Classifier: Intended Audience :: Science/Research
Classifier: License :: OSI Approved :: GNU General Public License v3 (GPLv3)
Classifier: Natural Language :: English
Classifier: Operating System :: OS Independent
Classifier: Programming Language :: Python :: 3.12
Classifier: Programming Language :: Python :: 3.13
Classifier: Topic :: Scientific/Engineering
Classifier: Topic :: Software Development
Classifier: Topic :: Software Development :: Libraries :: Python Modules
Classifier: Topic :: Software Development :: Version Control
Classifier: Topic :: Utilities
Requires-Python: >=3.12
Requires-Dist: asttokens>=3.0.0
Requires-Dist: regex>=2024.11.6
Provides-Extra: dev
Requires-Dist: pre-commit>=4.2.0; extra == 'dev'
Requires-Dist: ruff>=0.11.12; extra == 'dev'
Provides-Extra: testing
Requires-Dist: pytest>=8.3.5; extra == 'testing'
